cgPriceQuery/__init__.py
cgPriceQuery/blockTimestamps.py
cgPriceQuery/cgPriceQuery.py
cgPriceQuery/historicalPriceQuery.py
cgPriceQuery-0.0.0a9.dist-info/METADATA
cgPriceQuery-0.0.0a9.dist-info/WHEEL
cgPriceQuery-0.0.0a9.dist-info/top_level.txt
cgPriceQuery-0.0.0a9.dist-info/RECORD
