Metadata-Version: 2.1
Name: cgPriceQuery
Version: 0.0.0a9
Summary: Historical and current CoinGecko price queries
Home-page: https://github.com/gerrrg/cgPriceQuery
Author: gerrrg
Author-email: gerrrrrrrg@gmail.com
Project-URL: Bug Tracker, https://github.com/gerrrg/cgPriceQuery/issues
Classifier: Intended Audience :: Developers
Classifier: Programming Language :: Python :: 3
Classifier: License :: OSI Approved :: GNU General Public License v3 (GPLv3)
Classifier: Operating System :: OS Independent
Requires-Dist: alive-progress (==2.1.0)
Requires-Dist: gql (==2.0.0)
Requires-Dist: matplotlib (==3.5.1)
Requires-Dist: numpy (==1.22.0)
Requires-Dist: requests (>=2.25.1)
